setup.cfg
setup.py
cheater/__init__.py
cheater/app.py
cheater/cheatsheets_discovery.py
cheater/cli.py
cheater/render.py
cheater.egg-info/PKG-INFO
cheater.egg-info/SOURCES.txt
cheater.egg-info/dependency_links.txt
cheater.egg-info/entry_points.txt
cheater.egg-info/not-zip-safe
cheater.egg-info/requires.txt
cheater.egg-info/top_level.txt
cheater/cheatsheets/__init__.py
cheater/cheatsheets/stylesheet.css
cheater/cheatsheets/template.html