Metadata-Version: 1.1
Name: cheater
Version: 0.1.2
Summary: Cheater is a cheetsheet display app
Home-page: https://github.com/skalanux/cheater
Author: Juan Manuel Schillaci
Author-email: jmschillaci@gmail.com
License: GPLV3
Platform: any
Classifier: Development Status :: 3 - Alpha
Classifier: Environment :: Console
Classifier: Intended Audience :: Developers
Classifier: License :: OSI Approved :: GNU General Public License v3 (GPLv3)
Classifier: Operating System :: POSIX :: Linux
Classifier: Programming Language :: Python
Classifier: Programming Language :: Python :: 2
Classifier: Topic :: Software Development :: Libraries :: Python Modules
